{"Value":null,"VariableID":153015857,"Favorite":false,"UsesSQL":true,"SqlScript":"SELECT Requisition.*\r\nFROM Ariba.Requisition\r\nWHERE Requisition.RequisitionNumber = $[MSS_RequisitionNbr]","SqlServer":null,"SqlServerUAT":null,"SqlServerTraining":null,"SqlColumn":"RequisitionStatusID","SqlRow":1,"Note":"Result of the query showing the requisition status ID","Name":"MSS_QueryStatus","DateModified":null,"Description":null,"Program":"FTC","Browser":"Chrome","Environment":"Test","ServerEnvironment":"Test"}